odoo/addons/stock_inventory_line_product_cost/README.rst
odoo/addons/stock_inventory_line_product_cost/__init__.py
odoo/addons/stock_inventory_line_product_cost/__manifest__.py
odoo/addons/stock_inventory_line_product_cost/i18n/fr.po
odoo/addons/stock_inventory_line_product_cost/i18n/fr_FR.po
odoo/addons/stock_inventory_line_product_cost/i18n/it.po
odoo/addons/stock_inventory_line_product_cost/i18n/stock_inventory_line_product_cost.pot
odoo/addons/stock_inventory_line_product_cost/models/__init__.py
odoo/addons/stock_inventory_line_product_cost/models/stock_inventory_line.py
odoo/addons/stock_inventory_line_product_cost/static/description/icon.png
odoo/addons/stock_inventory_line_product_cost/views/stock_inventory_line_view.xml
odoo14_addon_stock_inventory_line_product_cost-14.0.1.0.1.dev10.dist-info/METADATA
odoo14_addon_stock_inventory_line_product_cost-14.0.1.0.1.dev10.dist-info/WHEEL
odoo14_addon_stock_inventory_line_product_cost-14.0.1.0.1.dev10.dist-info/top_level.txt
odoo14_addon_stock_inventory_line_product_cost-14.0.1.0.1.dev10.dist-info/RECORD
